README.rst
setup.py
virtstrap_npm/__init__.py
virtstrap_npm/plugin.py
virtstrap_npm.egg-info/PKG-INFO
virtstrap_npm.egg-info/SOURCES.txt
virtstrap_npm.egg-info/dependency_links.txt
virtstrap_npm.egg-info/entry_points.txt
virtstrap_npm.egg-info/not-zip-safe
virtstrap_npm.egg-info/requires.txt
virtstrap_npm.egg-info/top_level.txt