Metadata-Version: 1.0
Name: virtstrap-npm
Version: 0.0.3
Summary: A virtstrap plugin that installs node dependencies
Home-page: http://github.com/ravenac95/virtstrap-npm
Author: Reuven V. Gonzales
Author-email: reuven@tobetter.us
License: MIT
Keywords: virtstrap ruby bundler virtualenv pip
Platform: UNKNOWN
